weecfg/__init__.py
weecfg/database.py
weecfg/extension.py
weecfg/update_config.py
weectl.py
weectllib/__init__.py
weectllib/database_actions.py
weectllib/database_cmd.py
weectllib/debug_actions.py
weectllib/debug_cmd.py
weectllib/device_actions.py
weectllib/device_cmd.py
weectllib/extension_cmd.py
weectllib/import_actions.py
weectllib/import_cmd.py
weectllib/report_actions.py
weectllib/report_cmd.py
weectllib/station_actions.py
weectllib/station_cmd.py
weedb/NOTES.md
weedb/__init__.py
weedb/mysql.py
weedb/sqlite.py
weeimport/__init__.py
weeimport/csvimport.py
weeimport/cumulusimport.py
weeimport/wdimport.py
weeimport/weathercatimport.py
weeimport/weeimport.py
weeimport/wuimport.py
weeplot/__init__.py
weeplot/genplot.py
weeplot/utilities.py
weeutil/Moon.py
weeutil/Sun.py
weeutil/__init__.py
weeutil/config.py
weeutil/ftpupload.py
weeutil/log.py
weeutil/logger.py
weeutil/printer.py
weeutil/rsyncupload.py
weeutil/startup.py
weeutil/timediff.py
weeutil/weeutil.py
weewx/__init__.py
weewx/accum.py
weewx/almanac.py
weewx/cheetahgenerator.py
weewx/crc16.py
weewx/daemon.py
weewx/defaults.py
weewx/drivers/__init__.py
weewx/drivers/acurite.py
weewx/drivers/cc3000.py
weewx/drivers/fousb.py
weewx/drivers/simulator.py
weewx/drivers/te923.py
weewx/drivers/ultimeter.py
weewx/drivers/vantage.py
weewx/drivers/wmr100.py
weewx/drivers/wmr300.py
weewx/drivers/wmr9x8.py
weewx/drivers/ws1.py
weewx/drivers/ws23xx.py
weewx/drivers/ws28xx.py
weewx/engine.py
weewx/filegenerator.py
weewx/imagegenerator.py
weewx/manager.py
weewx/qc.py
weewx/reportengine.py
weewx/restx.py
weewx/schemas/__init__.py
weewx/schemas/wview.py
weewx/schemas/wview_extended.py
weewx/schemas/wview_small.py
weewx/station.py
weewx/tags.py
weewx/units.py
weewx/uwxutils.py
weewx/wxengine.py
weewx/wxformulas.py
weewx/wxmanager.py
weewx/wxservices.py
weewx/wxxtypes.py
weewx/xtypes.py
weewx_data/__init__.py
weewx_data/bin/user/__init__.py
weewx_data/bin/user/extensions.py
weewx_data/examples/alarm.py
weewx-5.2.0.dist-info/METADATA
weewx-5.2.0.dist-info/WHEEL
weewx-5.2.0.dist-info/entry_points.txt
weewx-5.2.0.dist-info/licenses/LICENSE.txt
weewx-5.2.0.dist-info/RECORD
