Metadata-Version: 2.4
Name: weewx
Version: 5.2.0
Summary: The WeeWX weather software system.
License: GPL3
License-File: LICENSE.txt
Author: Tom Keffer
Author-email: tkeffer@gmail.com
Requires-Python: >=3.7,<4.0
Classifier: Development Status :: 5 - Production/Stable
Classifier: Intended Audience :: End Users/Desktop
Classifier: Intended Audience :: Science/Research
Classifier: License :: OSI Approved :: GNU General Public License v3 (GPLv3)
Classifier: License :: Other/Proprietary License
Classifier: Operating System :: MacOS
Classifier: Operating System :: POSIX :: Linux
Classifier: Operating System :: Unix
Classifier: Programming Language :: Python
Classifier: Programming Language :: Python :: 3
Classifier: Programming Language :: Python :: 3.7
Classifier: Programming Language :: Python :: 3.8
Classifier: Programming Language :: Python :: 3.9
Classifier: Programming Language :: Python :: 3.10
Classifier: Programming Language :: Python :: 3.11
Classifier: Programming Language :: Python :: 3.12
Classifier: Programming Language :: Python :: 3.13
Classifier: Programming Language :: Python :: 3.14
Classifier: Topic :: Scientific/Engineering :: Physics
Requires-Dist: CT3 (>=3.1,<4.0)
Requires-Dist: Pillow (>=5.2)
Requires-Dist: PyMySQL (>=1.0,<2.0)
Requires-Dist: configobj (>=5.0,<6.0)
Requires-Dist: ephem (>=4.1,<5.0)
Requires-Dist: pyserial (>=3.4,<4.0)
Requires-Dist: pyusb (>=1.0.2,<2.0.0)
Project-URL: Documentation, https://weewx.com/docs
Project-URL: Homepage, https://weewx.com
Project-URL: Repository, https://github.com/weewx/weewx
